{
"meta":{"test_sets":[],"test_metrics":[],"learn_metrics":[{"best_value":"Min","name":"RMSE"}],"launch_mode":"Train","parameters":"","iteration_count":50,"learn_sets":["learn"],"name":"experiment"},
"iterations":[
{"learn":[4.519530824],"iteration":0,"passed_time":0.001129375635,"remaining_time":0.0553394061},
{"learn":[4.289376198],"iteration":1,"passed_time":0.002237972164,"remaining_time":0.05371133194},
{"learn":[4.105081083],"iteration":2,"passed_time":0.003352409481,"remaining_time":0.05252108187},
{"learn":[3.941722045],"iteration":3,"passed_time":0.00447160555,"remaining_time":0.05142346383},
{"learn":[3.815022684],"iteration":4,"passed_time":0.00559140316,"remaining_time":0.05032262844},
{"learn":[3.687364499],"iteration":5,"passed_time":0.006708355005,"remaining_time":0.04919460337},
{"learn":[3.558526412],"iteration":6,"passed_time":0.007786924822,"remaining_time":0.04783396676},
{"learn":[3.450297399],"iteration":7,"passed_time":0.008871025046,"remaining_time":0.04657288149},
{"learn":[3.353243528],"iteration":8,"passed_time":0.009925960588,"remaining_time":0.0452182649},
{"learn":[3.275712203],"iteration":9,"passed_time":0.01100867821,"remaining_time":0.04403471284},
{"learn":[3.212418107],"iteration":10,"passed_time":0.01209220756,"remaining_time":0.04287237227},
{"learn":[3.151508263],"iteration":11,"passed_time":0.01313668301,"remaining_time":0.04159949621},
{"learn":[3.093847655],"iteration":12,"passed_time":0.01417826322,"remaining_time":0.04035351839},
{"learn":[2.986831225],"iteration":13,"passed_time":0.01518564927,"remaining_time":0.03904881242},
{"learn":[2.928014273],"iteration":14,"passed_time":0.01626232573,"remaining_time":0.0379454267},
{"learn":[2.863662795],"iteration":15,"passed_time":0.01730855468,"remaining_time":0.0367806787},
{"learn":[2.820523161],"iteration":16,"passed_time":0.0183224027,"remaining_time":0.035567017},
{"learn":[2.763867866],"iteration":17,"passed_time":0.01937778888,"remaining_time":0.03444940246},
{"learn":[2.719336906],"iteration":18,"passed_time":0.02042191387,"remaining_time":0.03331996474},
{"learn":[2.691598528],"iteration":19,"passed_time":0.02144069116,"remaining_time":0.03216103675},
{"learn":[2.652465936],"iteration":20,"passed_time":0.02250894156,"remaining_time":0.03108377644},
{"learn":[2.603169063],"iteration":21,"passed_time":0.02356550997,"remaining_time":0.02999246724},
{"learn":[2.555209283],"iteration":22,"passed_time":0.02461834114,"remaining_time":0.02889979178},
{"learn":[2.531177528],"iteration":23,"passed_time":0.02569619942,"remaining_time":0.02783754937},
{"learn":[2.503784247],"iteration":24,"passed_time":0.02679066936,"remaining_time":0.02679066936},
{"learn":[2.461281817],"iteration":25,"passed_time":0.02780330489,"remaining_time":0.02566458913},
{"learn":[2.426142899],"iteration":26,"passed_time":0.0287933481,"remaining_time":0.0245276669},
{"learn":[2.405357316],"iteration":27,"passed_time":0.02986640755,"remaining_time":0.02346646307},
{"learn":[2.369805372],"iteration":28,"passed_time":0.03091801642,"remaining_time":0.02238890844},
{"learn":[2.343684494],"iteration":29,"passed_time":0.03191536318,"remaining_time":0.02127690878},
{"learn":[2.316525315],"iteration":30,"passed_time":0.03292231822,"remaining_time":0.02017819504},
{"learn":[2.280799852],"iteration":31,"passed_time":0.0339526773,"remaining_time":0.01909838098},
{"learn":[2.253995598],"iteration":32,"passed_time":0.03495799948,"remaining_time":0.0180086664},
{"learn":[2.228642914],"iteration":33,"passed_time":0.03599446025,"remaining_time":0.01693856953},
{"learn":[2.179440715],"iteration":34,"passed_time":0.03701719478,"remaining_time":0.01586451205},
{"learn":[2.140290519],"iteration":35,"passed_time":0.03808276012,"remaining_time":0.01480996227},
{"learn":[2.121987557],"iteration":36,"passed_time":0.0391196515,"remaining_time":0.01374474242},
{"learn":[2.077957845],"iteration":37,"passed_time":0.04018756126,"remaining_time":0.01269080882},
{"learn":[2.034755656],"iteration":38,"passed_time":0.04117844606,"remaining_time":0.0116144335},
{"learn":[2.007542908],"iteration":39,"passed_time":0.04226045254,"remaining_time":0.01056511314},
{"learn":[1.961836426],"iteration":40,"passed_time":0.04331346406,"remaining_time":0.009507833574},
{"learn":[1.917642287],"iteration":41,"passed_time":0.04435621626,"remaining_time":0.008448803098},
{"learn":[1.896541103],"iteration":42,"passed_time":0.04539241614,"remaining_time":0.007389463092},
{"learn":[1.853522604],"iteration":43,"passed_time":0.04644336417,"remaining_time":0.006333186024},
{"learn":[1.816192444],"iteration":44,"passed_time":0.04750097455,"remaining_time":0.005277886061},
{"learn":[1.778458189],"iteration":45,"passed_time":0.04860393026,"remaining_time":0.004226428718},
{"learn":[1.757889826],"iteration":46,"passed_time":0.04964785487,"remaining_time":0.003169012013},
{"learn":[1.725315497],"iteration":47,"passed_time":0.05073884807,"remaining_time":0.00211411867},
{"learn":[1.692543747],"iteration":48,"passed_time":0.05173025385,"remaining_time":0.001055719466},
{"learn":[1.651363611],"iteration":49,"passed_time":0.05273781002,"remaining_time":0}
]}