{
"meta":{"test_sets":[],"test_metrics":[],"learn_metrics":[{"best_value":"Min","name":"RMSE"}],"launch_mode":"Train","parameters":"","iteration_count":100,"learn_sets":["learn"],"name":"experiment"},
"iterations":[
{"learn":[4.506458333],"iteration":0,"passed_time":0.00401917536,"remaining_time":0.3978983606},
{"learn":[4.29750219],"iteration":1,"passed_time":0.007157992096,"remaining_time":0.3507416127},
{"learn":[4.141279755],"iteration":2,"passed_time":0.01063380317,"remaining_time":0.3438263023},
{"learn":[3.955429111],"iteration":3,"passed_time":0.01409396618,"remaining_time":0.3382551884},
{"learn":[3.800529893],"iteration":4,"passed_time":0.01755929847,"remaining_time":0.3336266709},
{"learn":[3.625194193],"iteration":5,"passed_time":0.02082905034,"remaining_time":0.3263217886},
{"learn":[3.522787613],"iteration":6,"passed_time":0.02413775203,"remaining_time":0.320687277},
{"learn":[3.39544995],"iteration":7,"passed_time":0.02761268152,"remaining_time":0.3175458375},
{"learn":[3.24848522],"iteration":8,"passed_time":0.03102489859,"remaining_time":0.3136961968},
{"learn":[3.134352717],"iteration":9,"passed_time":0.03447251912,"remaining_time":0.3102526721},
{"learn":[3.055217849],"iteration":10,"passed_time":0.03814913016,"remaining_time":0.308661144},
{"learn":[2.950405295],"iteration":11,"passed_time":0.04177416875,"remaining_time":0.3063439042},
{"learn":[2.90333524],"iteration":12,"passed_time":0.04477654129,"remaining_time":0.2996583917},
{"learn":[2.823031004],"iteration":13,"passed_time":0.04779347954,"remaining_time":0.2935885172},
{"learn":[2.75038054],"iteration":14,"passed_time":0.05084645259,"remaining_time":0.288129898},
{"learn":[2.707056968],"iteration":15,"passed_time":0.05378396886,"remaining_time":0.2823658365},
{"learn":[2.660336956],"iteration":16,"passed_time":0.05671392137,"remaining_time":0.2768973808},
{"learn":[2.600836887],"iteration":17,"passed_time":0.06016930603,"remaining_time":0.2741046164},
{"learn":[2.539147658],"iteration":18,"passed_time":0.06331119848,"remaining_time":0.2699056356},
{"learn":[2.489742876],"iteration":19,"passed_time":0.06623153375,"remaining_time":0.264926135},
{"learn":[2.425612409],"iteration":20,"passed_time":0.06921527289,"remaining_time":0.2603812647},
{"learn":[2.370672643],"iteration":21,"passed_time":0.07245667353,"remaining_time":0.2568918425},
{"learn":[2.307843478],"iteration":22,"passed_time":0.07553616391,"remaining_time":0.2528819401},
{"learn":[2.273689297],"iteration":23,"passed_time":0.07892999823,"remaining_time":0.2499449944},
{"learn":[2.225192767],"iteration":24,"passed_time":0.08191103252,"remaining_time":0.2457330975},
{"learn":[2.191110281],"iteration":25,"passed_time":0.08518145539,"remaining_time":0.2424395269},
{"learn":[2.138586712],"iteration":26,"passed_time":0.08835326147,"remaining_time":0.2388810403},
{"learn":[2.103413496],"iteration":27,"passed_time":0.09151264528,"remaining_time":0.2353182307},
{"learn":[2.067355463],"iteration":28,"passed_time":0.09483933923,"remaining_time":0.232192865},
{"learn":[2.035423088],"iteration":29,"passed_time":0.09817672214,"remaining_time":0.2290790183},
{"learn":[1.990315717],"iteration":30,"passed_time":0.1018410013,"remaining_time":0.2266783577},
{"learn":[1.941396596],"iteration":31,"passed_time":0.1051567254,"remaining_time":0.2234580414},
{"learn":[1.908432424],"iteration":32,"passed_time":0.108521317,"remaining_time":0.2203311589},
{"learn":[1.846573118],"iteration":33,"passed_time":0.1119164934,"remaining_time":0.2172496636},
{"learn":[1.809883817],"iteration":34,"passed_time":0.1150529663,"remaining_time":0.2136697946},
{"learn":[1.766922116],"iteration":35,"passed_time":0.1182968714,"remaining_time":0.2103055492},
{"learn":[1.724981734],"iteration":36,"passed_time":0.1215022377,"remaining_time":0.2068821885},
{"learn":[1.701959303],"iteration":37,"passed_time":0.1246516837,"remaining_time":0.2033790628},
{"learn":[1.676360831],"iteration":38,"passed_time":0.1276017322,"remaining_time":0.1995821965},
{"learn":[1.660056798],"iteration":39,"passed_time":0.1306325255,"remaining_time":0.1959487882},
{"learn":[1.612826206],"iteration":40,"passed_time":0.1335633195,"remaining_time":0.1922008744},
{"learn":[1.599419721],"iteration":41,"passed_time":0.1364127477,"remaining_time":0.1883795087},
{"learn":[1.576375182],"iteration":42,"passed_time":0.1392909572,"remaining_time":0.1846415014},
{"learn":[1.563720301],"iteration":43,"passed_time":0.1425031557,"remaining_time":0.1813676527},
{"learn":[1.524212666],"iteration":44,"passed_time":0.1454386381,"remaining_time":0.1777583355},
{"learn":[1.502887492],"iteration":45,"passed_time":0.1483526322,"remaining_time":0.17415309},
{"learn":[1.492521492],"iteration":46,"passed_time":0.1512780566,"remaining_time":0.170590149},
{"learn":[1.48183966],"iteration":47,"passed_time":0.1542303394,"remaining_time":0.1670828677},
{"learn":[1.452968582],"iteration":48,"passed_time":0.1572616434,"remaining_time":0.163680486},
{"learn":[1.417259395],"iteration":49,"passed_time":0.1602554005,"remaining_time":0.1602554005},
{"learn":[1.395488148],"iteration":50,"passed_time":0.1633801222,"remaining_time":0.1569730585},
{"learn":[1.35949384],"iteration":51,"passed_time":0.166699633,"remaining_time":0.1538765843},
{"learn":[1.334291805],"iteration":52,"passed_time":0.1701076025,"remaining_time":0.150850138},
{"learn":[1.303757812],"iteration":53,"passed_time":0.1735301478,"remaining_time":0.1478219778},
{"learn":[1.29067836],"iteration":54,"passed_time":0.1768579736,"remaining_time":0.1447019784},
{"learn":[1.265455847],"iteration":55,"passed_time":0.1798335381,"remaining_time":0.1412977799},
{"learn":[1.22929225],"iteration":56,"passed_time":0.1831907365,"remaining_time":0.1381965205},
{"learn":[1.202597045],"iteration":57,"passed_time":0.1861273209,"remaining_time":0.1347818531},
{"learn":[1.163733198],"iteration":58,"passed_time":0.1894688815,"remaining_time":0.131664816},
{"learn":[1.132929767],"iteration":59,"passed_time":0.1928186965,"remaining_time":0.1285457977},
{"learn":[1.127740785],"iteration":60,"passed_time":0.1962454699,"remaining_time":0.1254684152},
{"learn":[1.106784438],"iteration":61,"passed_time":0.1995026891,"remaining_time":0.1222758417},
{"learn":[1.074002645],"iteration":62,"passed_time":0.2026994399,"remaining_time":0.1190457028},
{"learn":[1.06306624],"iteration":63,"passed_time":0.2060430842,"remaining_time":0.1158992349},
{"learn":[1.042969729],"iteration":64,"passed_time":0.2090354785,"remaining_time":0.1125575653},
{"learn":[1.018060705],"iteration":65,"passed_time":0.21213778,"remaining_time":0.1092830988},
{"learn":[1.005595868],"iteration":66,"passed_time":0.2149828002,"remaining_time":0.1058870509},
{"learn":[0.9764390948],"iteration":67,"passed_time":0.218202432,"remaining_time":0.1026834974},
{"learn":[0.9484019294],"iteration":68,"passed_time":0.221287813,"remaining_time":0.09941916235},
{"learn":[0.920702281],"iteration":69,"passed_time":0.224257637,"remaining_time":0.09611041584},
{"learn":[0.8923450416],"iteration":70,"passed_time":0.2276345009,"remaining_time":0.09297747218},
{"learn":[0.8765089156],"iteration":71,"passed_time":0.2306168575,"remaining_time":0.08968433348},
{"learn":[0.8586032329],"iteration":72,"passed_time":0.2335899175,"remaining_time":0.08639627086},
{"learn":[0.8425427181],"iteration":73,"passed_time":0.2368357162,"remaining_time":0.08321254895},
{"learn":[0.8335360816],"iteration":74,"passed_time":0.2397189552,"remaining_time":0.0799063184},
{"learn":[0.8152182324],"iteration":75,"passed_time":0.2426019734,"remaining_time":0.07661114949},
{"learn":[0.7961532485],"iteration":76,"passed_time":0.2455535446,"remaining_time":0.07334716269},
{"learn":[0.7764520221],"iteration":77,"passed_time":0.2486969198,"remaining_time":0.07014528506},
{"learn":[0.7653939104],"iteration":78,"passed_time":0.2519242454,"remaining_time":0.06696720446},
{"learn":[0.7533742683],"iteration":79,"passed_time":0.2548548791,"remaining_time":0.06371371977},
{"learn":[0.7397587029],"iteration":80,"passed_time":0.2581097643,"remaining_time":0.0605442657},
{"learn":[0.7283678354],"iteration":81,"passed_time":0.2614224528,"remaining_time":0.05738541646},
{"learn":[0.7177859574],"iteration":82,"passed_time":0.2647532438,"remaining_time":0.05422656802},
{"learn":[0.6974874568],"iteration":83,"passed_time":0.2677937145,"remaining_time":0.05100832657},
{"learn":[0.6846301017],"iteration":84,"passed_time":0.2711291138,"remaining_time":0.04784631421},
{"learn":[0.6797292759],"iteration":85,"passed_time":0.2717310129,"remaining_time":0.04423528116},
{"learn":[0.656495344],"iteration":86,"passed_time":0.2747608044,"remaining_time":0.04105621214},
{"learn":[0.6361220937],"iteration":87,"passed_time":0.2780258879,"remaining_time":0.03791262107},
{"learn":[0.6273497839],"iteration":88,"passed_time":0.2814754621,"remaining_time":0.03478910206},
{"learn":[0.6148550119],"iteration":89,"passed_time":0.2847084681,"remaining_time":0.03163427423},
{"learn":[0.6062499709],"iteration":90,"passed_time":0.2877393616,"remaining_time":0.02845773906},
{"learn":[0.5949306436],"iteration":91,"passed_time":0.2907234008,"remaining_time":0.02528029572},
{"learn":[0.5845710815],"iteration":92,"passed_time":0.2937355709,"remaining_time":0.02210912899},
{"learn":[0.5797918223],"iteration":93,"passed_time":0.2971320095,"remaining_time":0.01896587295},
{"learn":[0.5680293106],"iteration":94,"passed_time":0.3002135738,"remaining_time":0.01580071441},
{"learn":[0.5559143399],"iteration":95,"passed_time":0.3036359188,"remaining_time":0.01265149662},
{"learn":[0.5470272299],"iteration":96,"passed_time":0.3070031152,"remaining_time":0.009494941707},
{"learn":[0.5386449572],"iteration":97,"passed_time":0.3100317544,"remaining_time":0.006327178661},
{"learn":[0.5273526888],"iteration":98,"passed_time":0.3132828226,"remaining_time":0.003164472955},
{"learn":[0.5204994492],"iteration":99,"passed_time":0.3161706494,"remaining_time":0}
]}