{"ongoing_trials": {}, "hyperparameters": {"space": [{"class_name": "Choice", "config": {"name": "learning_rate", "default": 0.01, "conditions": [], "values": [0.01, 0.001, 0.0001, 1e-05, 1e-06], "ordered": true}}, {"class_name": "Int", "config": {"name": "neuronios_camada_1", "default": null, "conditions": [], "min_value": 8, "max_value": 64, "step": 8, "sampling": "linear"}}, {"class_name": "Int", "config": {"name": "neuronios_camada_sequenciais", "default": null, "conditions": [], "min_value": 8, "max_value": 64, "step": 8, "sampling": "linear"}}, {"class_name": "Float", "config": {"name": "dropout", "default": 0.0, "conditions": [], "min_value": 0.0, "max_value": 0.5, "step": 0.1, "sampling": "linear"}}], "values": {"learning_rate": 0.01, "neuronios_camada_1": 8, "neuronios_camada_sequenciais": 8, "dropout": 0.0}}, "start_order": ["0", "1", "2", "3", "4"], "end_order": ["0", "1", "2", "3", "4"], "run_times": {"0": 1, "1": 1, "2": 1, "3": 1, "4": 1}, "retry_queue": [], "seed": 5012, "seed_state": 5032, "tried_so_far": ["55af5cc1350f1a8886688a5517cc2c61", "c6fcfbaf82b827c8bb0e863e35829e53", "763302745de2b1a5e1fcd552c7ff0beb", "1834ba5c4070fed5d42d32cdee470c57", "4e28927d75202507efbfff255818588f"], "id_to_hash": {"0": "c6fcfbaf82b827c8bb0e863e35829e53", "1": "1834ba5c4070fed5d42d32cdee470c57", "2": "4e28927d75202507efbfff255818588f", "3": "763302745de2b1a5e1fcd552c7ff0beb", "4": "55af5cc1350f1a8886688a5517cc2c61"}, "display": {"search_start": "2025-10-02T07:46:46.194538", "trial_start": {"0": "2025-10-02T07:46:46.194538", "1": "2025-10-02T07:46:56.327942", "2": "2025-10-02T07:47:07.104943", "3": "2025-10-02T07:47:18.376058", "4": "2025-10-02T07:47:29.601084"}, "trial_number": {"0": 1, "1": 2, "2": 3, "3": 4, "4": 5}}}